lmwrapper/_TokenStoppingCriteria.py
lmwrapper/__init__.py
lmwrapper/_sqlcache_utils_profile.py
lmwrapper/abstract_predictor.py
lmwrapper/batch_config.py
lmwrapper/caching.py
lmwrapper/compatibility.py
lmwrapper/env.py
lmwrapper/internals.py
lmwrapper/prompt_trimming.py
lmwrapper/runtime.py
lmwrapper/secrets_manager.py
lmwrapper/sqlcache.py
lmwrapper/sqlcache_struct.py
lmwrapper/structs.py
lmwrapper/togethertoy.py
lmwrapper/utils.py
lmwrapper/wrapping_config.py
lmwrapper/claude_wrapper/__init__.py
lmwrapper/claude_wrapper/wrapper.py
lmwrapper/huggingface_wrapper/__init__.py
lmwrapper/huggingface_wrapper/prediction.py
lmwrapper/huggingface_wrapper/predictor.py
lmwrapper/huggingface_wrapper/utilstorch.py
lmwrapper/huggingface_wrapper/wrapper.py
lmwrapper/openai_wrapper/__init__.py
lmwrapper/openai_wrapper/batching.py
lmwrapper/openai_wrapper/wrapper.py
lmwrapper-0.18.0.0.dist-info/METADATA
lmwrapper-0.18.0.0.dist-info/WHEEL
lmwrapper-0.18.0.0.dist-info/top_level.txt
lmwrapper-0.18.0.0.dist-info/RECORD
