Metadata-Version: 2.4
Name: lmwrapper
Version: 0.18.0.0
Summary: An object-oriented wrapper around language models with caching, batching, and more. 
Author: David Gros, Claudio Spiess
Project-URL: Homepage, https://github.com/DaiseyCode/lmwrapper
Keywords: large language models,openai
Classifier: Programming Language :: Python :: 3
Requires-Python: >=3.10
Requires-Dist: openai~=1.55.3
Requires-Dist: tiktoken~=0.7.0
Requires-Dist: ratemate~=0.1
Requires-Dist: humanize~=4.8.0
Requires-Dist: xxhash~=3.4
Requires-Dist: numpy~=1.24
Requires-Dist: packaging>=22.0
Provides-Extra: dev
Requires-Dist: black~=23.10.0; extra == "dev"
Requires-Dist: ruff~=0.1.1; extra == "dev"
Requires-Dist: pytest~=7.4.2; extra == "dev"
Requires-Dist: pytest-cov~=4.1.0; extra == "dev"
Requires-Dist: build~=1.0.3; extra == "dev"
Requires-Dist: twine~=5.1.1; extra == "dev"
Provides-Extra: quant
Requires-Dist: bitsandbytes~=0.41.1; extra == "quant"
Provides-Extra: hf
Requires-Dist: torch~=2.3.0; extra == "hf"
Requires-Dist: transformers~=4.46.3; extra == "hf"
Provides-Extra: anthropic
Requires-Dist: anthropic~=0.54.0; extra == "anthropic"
Provides-Extra: docs
Requires-Dist: mkdocs>=1.4.0; extra == "docs"
Requires-Dist: mkdocstrings[python]>=0.24.0; extra == "docs"
Requires-Dist: mkdocs-material>=9.0.0; extra == "docs"
Requires-Dist: mike>=1.1.2; extra == "docs"
Provides-Extra: accelerate
Requires-Dist: accelerate~=0.23.0; extra == "accelerate"
Provides-Extra: xformers
Requires-Dist: xformers~=0.0.22; extra == "xformers"
Provides-Extra: flash-attn
Requires-Dist: flash_attn~=2.3.2; extra == "flash-attn"
Provides-Extra: ort
Requires-Dist: optimum[onnxruntime]~=1.13.2; extra == "ort"
Provides-Extra: ort-gpu
Requires-Dist: optimum[onnxruntime-gpu]~=1.13.2; extra == "ort-gpu"
